.bzrignore
HISTORY.txt
README.txt
demoapp-paster.ini
setup.cfg
setup.py
src/ClueDojo.egg-info/PKG-INFO
src/ClueDojo.egg-info/SOURCES.txt
src/ClueDojo.egg-info/dependency_links.txt
src/ClueDojo.egg-info/entry_points.txt
src/ClueDojo.egg-info/not-zip-safe
src/ClueDojo.egg-info/requires.txt
src/ClueDojo.egg-info/top_level.txt
src/cluedojo/__init__.py
src/cluedojo/demoapp.py
src/cluedojo/wsgiapp.py
src/cluedojo/static/dijit/Calendar.js
src/cluedojo/static/dijit/CheckedMenuItem.js
src/cluedojo/static/dijit/ColorPalette.js
src/cluedojo/static/dijit/Declaration.js
src/cluedojo/static/dijit/Dialog.js
src/cluedojo/static/dijit/DialogUnderlay.js
src/cluedojo/static/dijit/Editor.js
src/cluedojo/static/dijit/InlineEditBox.js
src/cluedojo/static/dijit/LICENSE
src/cluedojo/static/dijit/Menu.js
src/cluedojo/static/dijit/MenuBar.js
src/cluedojo/static/dijit/MenuBarItem.js
src/cluedojo/static/dijit/MenuItem.js
src/cluedojo/static/dijit/MenuSeparator.js
src/cluedojo/static/dijit/PopupMenuBarItem.js
src/cluedojo/static/dijit/PopupMenuItem.js
src/cluedojo/static/dijit/ProgressBar.js
src/cluedojo/static/dijit/TitlePane.js
src/cluedojo/static/dijit/Toolbar.js
src/cluedojo/static/dijit/ToolbarSeparator.js
src/cluedojo/static/dijit/Tooltip.js
src/cluedojo/static/dijit/TooltipDialog.js
src/cluedojo/static/dijit/Tree.js
src/cluedojo/static/dijit/_Calendar.js
src/cluedojo/static/dijit/_Contained.js
src/cluedojo/static/dijit/_Container.js
src/cluedojo/static/dijit/_DialogMixin.js
src/cluedojo/static/dijit/_HasDropDown.js
src/cluedojo/static/dijit/_KeyNavContainer.js
src/cluedojo/static/dijit/_Templated.js
src/cluedojo/static/dijit/_TimePicker.js
src/cluedojo/static/dijit/_Widget.js
src/cluedojo/static/dijit/_base.js
src/cluedojo/static/dijit/dijit-all.js
src/cluedojo/static/dijit/dijit-all.js.uncompressed.js
src/cluedojo/static/dijit/dijit.js
src/cluedojo/static/dijit/dijit.js.uncompressed.js
src/cluedojo/static/dijit/robot.js
src/cluedojo/static/dijit/robotx.js
src/cluedojo/static/dijit/_base/focus.js
src/cluedojo/static/dijit/_base/manager.js
src/cluedojo/static/dijit/_base/place.js
src/cluedojo/static/dijit/_base/popup.js
src/cluedojo/static/dijit/_base/scroll.js
src/cluedojo/static/dijit/_base/sniff.js
