Metadata-Version: 1.0
Name: ClueDojo
Version: 1.4.3-1
Summary: Simple Python library to access the Dojo Javascript toolkit
Home-page: https://dev.serverzen.com/svn/cluemapper/ClueDojo/
Author: Rocky Burt
Author-email: rocky@serverzen.com
License: BSD
Keywords: wsgi dojo javascript ajax
Platform: UNKNOWN
Classifier: License :: OSI Approved :: BSD License
Classifier: Programming Language :: JavaScript
Classifier: Programming Language :: Python
Classifier: Topic :: Internet :: WWW/HTTP :: WSGI
Classifier: Topic :: Software Development :: Libraries :: Python Modules
